visionai/__init__.py
visionai/__main__.py
visionai/apiutils/api.py
visionai/cli/README.md
visionai/cli/__init__.py
visionai/cli/auth_app.py
visionai/cli/camera_app.py
visionai/cli/commands.py
visionai/cli/device_app.py
visionai/cli/get_config_values.py
visionai/cli/license.py
visionai/cli/models_app.py
visionai/cli/pipeline_app.py
visionai/cli/scenario_app.py
visionai/cli/start_stop_influx_db.py
visionai/cli/start_stop_model_server.py
visionai/cli/start_stop_redis_grafana.py
visionai/cli/start_stop_web_app.py
visionai/cli/stop_cmd.py
visionai/cli/web_app.py
visionai/config/.gitignore
visionai/config/.gitkeep
visionai/config/camera-schema.json
visionai/config/download_schema.py
visionai/config.py
visionai/events/__init__.py
visionai/events/events_engine.py
visionai/main.py
visionai/models/.gitignore
visionai/models/README.md
visionai/models/__init__.py
visionai/models/common.py
visionai/models/plots.py
visionai/models/triton_client.py
visionai/models/triton_client_yolov5.py
visionai/models-repo/.gitignore
visionai/models-repo/.gitkeep
visionai/scenarios/README.md
visionai/scenarios/__init__.py
visionai/scenarios/capture_media.py
visionai/scenarios/ergonomics_detection.py
visionai/scenarios/face_blur.py
visionai/scenarios/firearms_detection.py
visionai/scenarios/occupancy_monitoring.py
visionai/scenarios/people_taking_picture_detection.py
visionai/scenarios/ppe_detection.py
visionai/scenarios/productivity_detection.py
visionai/scenarios/restricted_zone.py
visionai/scenarios/scenarios.json
visionai/scenarios/slip_and_fall_detection.py
visionai/scenarios/smoke_and_fire_detection.py
visionai/scenarios/smoking_detection.py
visionai/tests/__init__.py
visionai/tests/docker-compose.yml
visionai/tests/test_cli_auth.py
visionai/tests/test_cli_camera.py
visionai/tests/test_cli_device.py
visionai/tests/test_cli_main.py
visionai/tests/test_cli_models.py
visionai/tests/test_cli_pipeline.py
visionai/tests/test_cli_scenario.py
visionai/tests/test_cli_stop_cmd.py
visionai-0.3.22.dist-info/LICENSE
visionai-0.3.22.dist-info/METADATA
visionai-0.3.22.dist-info/WHEEL
visionai-0.3.22.dist-info/entry_points.txt
visionai-0.3.22.dist-info/RECORD
