Metadata-Version: 2.1
Name: visionai
Version: 0.3.22
Summary: Vision AI toolkit
License: VPSLA 1.0
Author: Harsh Murari
Author-email: hmurari@visionify.ai
Requires-Python: >=3.10,<4.0
Classifier: License :: Other/Proprietary License
Classifier: Programming Language :: Python :: 3
Classifier: Programming Language :: Python :: 3.10
Classifier: Programming Language :: Python :: 3.11
Classifier: Programming Language :: Python :: 3.12
Requires-Dist: coloredlogs (>=15.0.0)
Requires-Dist: docker (>=5.0.3,<7.0.0)
Requires-Dist: pytest (>=7.2.1,<8.0.0)
Requires-Dist: pyyaml (>=5.4.1,<7.0.0)
Requires-Dist: requests (>=2.28.2,<3.0.0)
Requires-Dist: typer[all] (>=0.7,<0.10)
Requires-Dist: validators (>=0.22.0,<0.23.0)
